python_snake_game/__init__.py
python_snake_game/__main__.py
python_snake_game/utilities.py
python_snake_game-1.0.10.dist-info/licenses/LICENSE.txt
python_snake_game-1.0.10.dist-info/METADATA
python_snake_game-1.0.10.dist-info/WHEEL
python_snake_game-1.0.10.dist-info/top_level.txt
python_snake_game-1.0.10.dist-info/RECORD
