Metadata-Version: 2.4
Name: python_snake_game
Version: 1.0.10
Summary: A simple Snake game written in Python for the command-line interface (CLI). Control the snake with arrow keys, eat food to grow, and avoid running into yourself. Built entirely with Python's standard libraries-no third-party packages required.
Author: ramimK0bir
Author-email: kobirbiddut81@gmail.com
Classifier: Programming Language :: Python :: 3
Classifier: Operating System :: Microsoft :: Windows
Classifier: Operating System :: POSIX :: Linux
Classifier: License :: OSI Approved :: MIT License
Requires-Python: >=3.7
License-File: LICENSE.txt
Dynamic: author
Dynamic: author-email
Dynamic: classifier
Dynamic: description
Dynamic: description-content-type
Dynamic: license-file
Dynamic: requires-python
Dynamic: summary
